gadlogging/__init__.py
gadlogging/const/__init__.py
gadlogging/const/logging.py
gadlogging/const/symbols.py
gadlogging/formatters/__init__.py
gadlogging/formatters/base.py
gadlogging/formatters/json.py
gadlogging/formatters/plain.py
gadlogging/mappers/__init__.py
gadlogging/mappers/logging.py
gadlogging/models/__init__.py
gadlogging/models/logging.py
gadlogging/utils/__init__.py
gadlogging/utils/config.py
gadlogging/utils/fields.py
tests/__init__.py
tests/test_init.py
gadlogging-0.0.1.dist-info/LICENSE
gadlogging-0.0.1.dist-info/METADATA
gadlogging-0.0.1.dist-info/WHEEL
gadlogging-0.0.1.dist-info/top_level.txt
gadlogging-0.0.1.dist-info/RECORD
